devtools/shader_viewer.py
devtools/test_graph.py
examples/gyroid.py
examples/simple_demo.py
tests/__init__.py
topax/__init__.py
topax/_app.py
topax/_shaders.py
topax/_utils.py
topax/_version.py
topax/ops.py
topax/sdfs.py
topax/templates/shader.glsl.j2
topax-0.1.0.dist-info/licenses/LICENSE
topax-0.1.0.dist-info/METADATA
topax-0.1.0.dist-info/WHEEL
topax-0.1.0.dist-info/entry_points.txt
topax-0.1.0.dist-info/top_level.txt
topax-0.1.0.dist-info/RECORD
