Metadata-Version: 2.4
Name: topax
Version: 0.1.0
Summary: Topax - A Full Stack Implicit Geometry CAD Package for Python
Author: Andy
License-Expression: AGPL-3.0
Project-URL: Source, https://github.com/andycate/topax
Requires-Python: >=3.11
License-File: LICENSE
Requires-Dist: numpy
Requires-Dist: PyOpenGL
Requires-Dist: PyOpenGL_accelerate
Requires-Dist: glfw
Requires-Dist: watchdog
Requires-Dist: ipython
Requires-Dist: jinja2
Dynamic: license-file
